pydtk/__init__.py
pydtk/bin/__init__.py
pydtk/bin/cli.py
pydtk/bin/make_meta.py
pydtk/bin/oas.py
pydtk/bin/sub_commands/__init__.py
pydtk/bin/sub_commands/db.py
pydtk/bin/sub_commands/io.py
pydtk/bin/sub_commands/model.py
pydtk/bin/sub_commands/status.py
pydtk/builder/__init__.py
pydtk/builder/concat_df.py
pydtk/builder/dbdb/__init__.py
pydtk/builder/dbdb/file_info.py
pydtk/builder/df_list.py
pydtk/builder/df_path.py
pydtk/builder/meta_db.py
pydtk/builder/statistic_db.py
pydtk/conf/v1.yaml
pydtk/conf/v2.yaml
pydtk/conf/v3.yaml
pydtk/conf/v4.yaml
pydtk/db/__init__.py
pydtk/db/exceptions.py
pydtk/db/schemas/__init__.py
pydtk/db/schemas/dataware-tools.com/__init__.py
pydtk/db/schemas/dataware-tools.com/v1alpha1/__init__.py
pydtk/db/schemas/dataware-tools.com/v1alpha1/annotation.py
pydtk/db/schemas/dataware-tools.com/v1alpha1/annotation_commented_image_pixel.py
pydtk/db/schemas/dataware-tools.com/v1alpha1/annotation_commented_image_rectangular_area.py
pydtk/db/schemas/dataware-tools.com/v1alpha1/annotation_commented_point.py
pydtk/db/schemas/dataware-tools.com/v1alpha1/file.py
pydtk/db/schemas/dataware-tools.com/v1alpha1/record.py
pydtk/db/schemas/dataware-tools.com/v1alpha2/__init__.py
pydtk/db/schemas/dataware-tools.com/v1alpha2/annotation.py
pydtk/db/schemas/dataware-tools.com/v1alpha2/annotation_commented_image_pixel.py
pydtk/db/schemas/dataware-tools.com/v1alpha2/annotation_commented_image_rectangular_area.py
pydtk/db/schemas/dataware-tools.com/v1alpha2/annotation_commented_point.py
pydtk/db/schemas/dataware-tools.com/v1alpha2/file.py
pydtk/db/schemas/dataware-tools.com/v1alpha2/record.py
pydtk/db/schemas/dataware-tools.com/v1alpha3/__init__.py
pydtk/db/schemas/dataware-tools.com/v1alpha3/annotation.py
pydtk/db/schemas/dataware-tools.com/v1alpha3/annotation_commented_image_pixel.py
pydtk/db/schemas/dataware-tools.com/v1alpha3/annotation_commented_image_rectangular_area.py
pydtk/db/schemas/dataware-tools.com/v1alpha3/annotation_commented_point.py
pydtk-0.3.2.dist-info/LICENSE
pydtk-0.3.2.dist-info/METADATA
pydtk-0.3.2.dist-info/WHEEL
pydtk-0.3.2.dist-info/entry_points.txt
pydtk-0.3.2.dist-info/RECORD
