Metadata-Version: 2.1
Name: pydtk
Version: 0.3.2
Summary: A Python toolkit for managing, retrieving and processing data.
Home-page: https://github.com/dataware-tools/python-toolkit.git
License: Apache-2.0
Keywords: toolkit,data,dataware,metadata
Author: Yusuke Adachi
Author-email: adachi.yusuke@hdwlab.co.jp
Requires-Python: >=3.8,<3.11
Classifier: License :: OSI Approved :: Apache Software License
Classifier: Operating System :: POSIX :: Linux
Classifier: Programming Language :: Python :: 3
Classifier: Programming Language :: Python :: 3.8
Classifier: Programming Language :: Python :: 3.9
Classifier: Programming Language :: Python :: 3.10
Classifier: Topic :: Software Development :: Libraries :: Python Modules
Provides-Extra: pointcloud
Provides-Extra: ros
Provides-Extra: ros2
Provides-Extra: zstd
Requires-Dist: addict (>=2.4.0,<3.0.0)
Requires-Dist: bitstring (>=3.1.7,<4.0.0)
Requires-Dist: deepmerge (>=0.1.1,<0.2.0)
Requires-Dist: fire (>=0.3.1,<0.4.0)
Requires-Dist: flatdict (>=4.0.1,<5.0.0) ; extra == "ros" or extra == "ros2"
Requires-Dist: flatten-dict (>=0.3.0,<0.4.0)
Requires-Dist: gnupg ; extra == "ros"
Requires-Dist: iso8601 (>=1.1.0,<2.0.0)
Requires-Dist: lark (>=1.1.5,<2.0.0) ; extra == "ros2"
Requires-Dist: montydb[bson,lmdb] (>=2.4.0,<3.0.0)
Requires-Dist: numpy (<1.24.0)
Requires-Dist: opencv-python (>=4.2.0.34,<5.0.0.0)
Requires-Dist: pandas (>=1.0.3,<2.0.0)
Requires-Dist: pycryptodomex ; extra == "ros"
Requires-Dist: pydantic (>=1.10.2,<2.0.0)
Requires-Dist: pymongo (>=3.11.3,<4.0.0)
Requires-Dist: pyntcloud ; extra == "pointcloud"
Requires-Dist: python-dateutil (>=2.8.1,<3.0.0)
Requires-Dist: pyyaml
Requires-Dist: pyzstd (>=0.15.0,<0.16.0) ; extra == "zstd"
Requires-Dist: rospkg ; extra == "ros"
Requires-Dist: scipy (>=1.8.0,<2.0.0)
Requires-Dist: six (>=1.15.0,<2.0.0)
Requires-Dist: sqlalchemy (>=1.3.17,<2.0.0)
Requires-Dist: sqlalchemy-migrate
Requires-Dist: tinydb (>=3.2.1,<4.0.0)
Requires-Dist: tinymongo (>=0.2.0,<0.3.0)
Requires-Dist: tqdm (>=4.46.1,<5.0.0)
Project-URL: Repository, https://github.com/dataware-tools/python-toolkit.git
